graviti/__init__.py
graviti/__version__.py
graviti/exception.py
graviti/py.typed
graviti/dataframe/__init__.py
graviti/dataframe/container.py
graviti/dataframe/frame.py
graviti/dataframe/indexing.py
graviti/dataframe/column/__init__.py
graviti/dataframe/column/indexing.py
graviti/dataframe/column/series.py
graviti/dataframe/row/__init__.py
graviti/dataframe/row/indexing.py
graviti/dataframe/row/series.py
graviti/dataframe/sql/__init__.py
graviti/dataframe/sql/array.py
graviti/dataframe/sql/container.py
graviti/dataframe/sql/operator.py
graviti/dataframe/sql/scalar.py
graviti/file/__init__.py
graviti/file/audio.py
graviti/file/base.py
graviti/file/image.py
graviti/file/image_size.py
graviti/file/point_cloud.py
graviti/manager/__init__.py
graviti/manager/action.py
graviti/manager/branch.py
graviti/manager/commit.py
graviti/manager/common.py
graviti/manager/dataset.py
graviti/manager/draft.py
graviti/manager/lazy.py
graviti/manager/permission.py
graviti/manager/search.py
graviti/manager/sheets.py
graviti/manager/storage_config.py
graviti/manager/tag.py
graviti/manager/workspace.py
graviti/openapi/__init__.py
graviti/openapi/action.py
graviti/openapi/branch.py
graviti/openapi/commit.py
graviti/openapi/data.py
graviti/openapi/dataset.py
graviti/openapi/draft.py
graviti/openapi/object.py
graviti/openapi/record.py
graviti/openapi/requests.py
graviti/openapi/schema.py
graviti/openapi/search.py
graviti/openapi/sheet.py
graviti/openapi/storage_config.py
graviti/openapi/tag.py
graviti/openapi/user.py
graviti/openapi/workspace.py
graviti/operation/__init__.py
graviti/operation/common.py
graviti/operation/frame.py
graviti/operation/sheet.py
graviti/paging/__init__.py
graviti/paging/factory.py
graviti/paging/lists.py
graviti/paging/offset.py
graviti/paging/page.py
graviti/paging/wrapper.py
graviti/portex/__init__.py
graviti/portex/avro.py
graviti/portex/base.py
graviti/portex/builder.py
graviti/portex/builtin.py
graviti/portex/enum.py
graviti/portex/external.py
graviti-0.13.1.dist-info/LICENSE
graviti-0.13.1.dist-info/METADATA
graviti-0.13.1.dist-info/WHEEL
graviti-0.13.1.dist-info/top_level.txt
graviti-0.13.1.dist-info/RECORD
