Metadata-Version: 2.1
Name: graviti
Version: 0.13.1
Summary: Graviti Python SDK
Home-page: https://github.com/Graviti-AI/graviti-python-sdk
Author: Graviti
Author-email: pypi@graviti.com
License: MIT
Keywords: graviti,dataset,DataFrame
Platform: UNKNOWN
Classifier: Development Status :: 2 - Pre-Alpha
Classifier: Intended Audience :: Developers
Classifier: Intended Audience :: Science/Research
Classifier: License :: OSI Approved :: MIT License
Classifier: Operating System :: OS Independent
Classifier: Programming Language :: Python
Classifier: Programming Language :: Python :: 3
Classifier: Programming Language :: Python :: 3 :: Only
Classifier: Programming Language :: Python :: 3.6
Classifier: Programming Language :: Python :: 3.7
Classifier: Programming Language :: Python :: 3.8
Classifier: Programming Language :: Python :: 3.9
Classifier: Topic :: Scientific/Engineering :: Artificial Intelligence
Classifier: Typing :: Typed
Requires-Python: >=3.6
Requires-Dist: urllib3 (>=1.15)
Requires-Dist: requests (>=2.4.2)
Requires-Dist: requests-toolbelt (>=0.3.0)
Requires-Dist: pyyaml (>=5.1)
Requires-Dist: pyarrow (>=3.0.0)
Requires-Dist: tqdm (>=4.27.0)
Requires-Dist: typing-extensions (>=3.7.2)
